core_evals/ifbench/__init__.py
core_evals/ifbench/framework.yml
core_evals/ifbench/framework_entrypoint.py
core_evals/ifbench/output.py
ifbench/__init__.py
ifbench/args.py
ifbench/callbacks.py
ifbench/evaluation_lib.py
ifbench/instructions.py
ifbench/instructions_registry.py
ifbench/instructions_test.py
ifbench/instructions_util.py
ifbench/run_eval.py
ifbench/data/IFBench_test.jsonl
ifbench/data/sample_output.jsonl
nvidia_ifbench-25.11.dist-info/licenses/LICENSE
nvidia_ifbench-25.11.dist-info/METADATA
nvidia_ifbench-25.11.dist-info/WHEEL
nvidia_ifbench-25.11.dist-info/entry_points.txt
nvidia_ifbench-25.11.dist-info/top_level.txt
nvidia_ifbench-25.11.dist-info/RECORD
