Metadata-Version: 2.4
Name: nvidia-ifbench
Version: 25.11
Summary: IFBench: A challenging benchmark for precise instruction following
License:                                  Apache License
Project-URL: Original Project, https://github.com/allenai/IFBench
Project-URL: Paper, https://arxiv.org/abs/2402.18676
Classifier: Development Status :: 5 - Production/Stable
Classifier: Programming Language :: Python :: 3
Classifier: License :: OSI Approved :: Apache Software License
Classifier: Operating System :: OS Independent
Requires-Python: >=3.10
License-File: LICENSE
Requires-Dist: absl-py
Requires-Dist: langdetect
Requires-Dist: nltk
Requires-Dist: immutabledict
Requires-Dist: spacy
Requires-Dist: emoji
Requires-Dist: syllapy
Requires-Dist: unicodedata2
Requires-Dist: langchain
Requires-Dist: langchain-openai
Requires-Dist: tqdm
Requires-Dist: jsonlines
Requires-Dist: nemo-evaluator
Dynamic: license-file
